annex4nlp/__init__.py
annex4nlp/cli.py
annex4nlp/review.py
annex4nlp-1.0.1.dist-info/licenses/LICENSE
annex4nlp-1.0.1.dist-info/licenses/THIRD_PARTY_LICENSES.md
annex4nlp-1.0.1.dist-info/METADATA
annex4nlp-1.0.1.dist-info/WHEEL
annex4nlp-1.0.1.dist-info/entry_points.txt
annex4nlp-1.0.1.dist-info/top_level.txt
annex4nlp-1.0.1.dist-info/RECORD
