Metadata-Version: 2.4
Name: annex4nlp
Version: 1.0.1
Summary: NLP-based compliance analysis for EU AI Act Annex IV documents
Author-email: Aleksandr Racionalus <prihodko02bk@gmail.com>
License-Expression: MIT
Keywords: AI Act,compliance,NLP,text analysis
Requires-Python: >=3.9
License-File: LICENSE
License-File: THIRD_PARTY_LICENSES.md
Requires-Dist: typer[all]>=0.12
Requires-Dist: spacy>=3.7.5
Requires-Dist: negspacy>=1.0.4
Requires-Dist: PyPDF2>=3.0
Requires-Dist: pdfplumber>=0.10
Requires-Dist: PyMuPDF>=1.23
Requires-Dist: nltk>=3.8
Requires-Dist: spacy-lookups-data>=1.0
Dynamic: license-file
